doglib/__init__.py
doglib/catlib.py
doglib/main.py
doglib-0.1.2.dist-info/LICENSE
doglib-0.1.2.dist-info/METADATA
doglib-0.1.2.dist-info/WHEEL
doglib-0.1.2.dist-info/top_level.txt
doglib-0.1.2.dist-info/RECORD
