Metadata-Version: 2.1
Name: doglib
Version: 0.1.2
Summary: Doglib ist eine Python-Bibliothek, die speziell entwickelt wurde, um Schülerinnen die grundlegenden Arbeitsprinzipien von Python-Bibliotheken auf einfache und unterhaltsame Weise zu erklären.
Author: Starcode
Author-email: info@starcode.de
Classifier: Programming Language :: Python :: 3
Classifier: License :: OSI Approved :: MIT License
Classifier: Operating System :: OS Independent
Requires-Python: >=3.6
License-File: LICENSE
Requires-Dist: numpy
